{
  "ua": "Mozilla/5.0 (iPhone; CPU iPhone OS 13_2_3 like Mac OS X) AppleWebKit/605.1.15 (KHTML, like Gecko) Version/13.0.3 Mobile/15E148 Safari/604.1",
  "homeUrl": "https://vipmv.tv",
  "dcVipFlag": "true",
  "pCfgJs": "https://vipmv.tv/static/js/playerconfig.js",
  "pCfgJsR": "[\\W|\\S|.]*?MacPlayerConfig.player_list[\\W|\\S|.]*?=([\\W|\\S|.]*?),MacPlayerConfig.downer_list",
  "dcShow2Vip": {},
  "dcPlayUrl": "true",
  "cateManual": {"爱情片":"8","剧情片":"11","动作片":"6","喜剧片":"7","科幻片":"9","恐怖片":"10","战争片":"12","国产剧":"13","欧美剧":"16","日韩剧":"15","港台剧":"14","综艺":"3","动漫":"4"},
  "homeVodNode": "//div[contains(@class,'pack-ykpack')]/div/a[contains(@class,'aplus-exp')]",
  "homeVodName": "/@title",
  "homeVodId": "/@href",
  "homeVodIdR": "/Moviedetail/(\\w+).html",
  "homeVodImg": "/div/@data-original",
  "homeVodImgR": "\\S+(http\\S+)",
  "homeVodMark": "//span[contains(@class,'pack-prb')]/text()",
  "cateUrl": "https://vipmv.tv/vodshow/{cateId}-{area}-{by}-{class}-----{catePg}---{year}.html",
  "cateVodNode": "//div[contains(@class,'pack-ykpack')]/div/a[contains(@class,'aplus-exp')]",
  "cateVodName": "/@title",
  "cateVodId": "/@href",
  "cateVodIdR": "/Moviedetail/(\\w+).html",
  "cateVodImg": "/div/@data-original",
  "cateVodImgR": "\\S+(http\\S+)",
  "cateVodMark": "//span[contains(@class,'pack-prb')]/text()",
  "dtUrl": "https://vipmv.tv/Moviedetail/{vid}.html",
  "dtNode": "//body",
  "dtName": "//div[@class='s-top-right']/div/h1/text()",
  "dtNameR": "",
  "dtImg": "//div[@class='s-cover box']/a/img/@src",
  "dtImgR": "",
  "dtCate": "//div[@class='s-top-right']/div/p/span[contains(text(), '类型')]/following-sibling::*/text()",
  "dtYear": "//span[contains(text(), '年代')]/following-sibling::a/text()",
  "dtArea": "//span[contains(text(), '地区')]/following-sibling::a/text()",
  "dtMark": "//span[contains(text(), '地区')]/following-sibling::a/text()",
  "dtDirector": "//span[contains(text(), '导演')]/following-sibling::a/text()",
  "dtActor": "//span[contains(text(), '演员')]/following-sibling::a/text()",
  "dtDesc": "//span[contains(text(), '简介')]/following-sibling::span/text()",
  "dtFromNode": "//div[@class='play_source']/div/div/a",
  "dtFromName": "[substring-before(text(),'(')]",
  "dtFromNameR": "",
  "dtUrlNode": "//div[@class='playlist_notfull']/ul",
  "dtUrlSubNode": "/li/a",
  "dtUrlId": "/@href",
  "dtUrlIdR": "/okplay/(\\S+).html",
  "dtUrlName": "/text()",
  "dtUrlNameR": "",
  "playUrl": "https://vipmv.tv/okplay/{playUrl}.html",
  "playUa": "",
  "searchUrl": "https://vipmv.tv/index.php/ajax/suggest?mid=1&wd={wd}&limit=10",
  "scVodNode": "json:list",
  "scVodName": "name",
  "scVodId": "id",
  "scVodIdR": "",
  "scVodImg": "pic",
  "scVodMark": "",
  "filter": {
    "3": [
      {"key":"area","name":"地区","value":[{"n":"全部","v":""},
        {"n":"大陆","v":"内地"},
        {"n":"港台","v":"港台"},
        {"n":"欧美","v":"欧美"},
        {"n":"美国","v":"美国"}
      ]},
      {"key":"year","name":"年份","value": [{"n":"全部","v":""},
        {"n":"2022","v":"2022"},{"n":"2021","v":"2021"},{"n":"2020","v":"2020"},{"n":"2019","v":"2019"},
        {"n":"2018","v":"2018"},{"n":"2017","v":"2017"},{"n":"2016","v":"2016"},{"n":"2015","v":"2015"},
        {"n":"2014","v":"2014"},{"n":"2013","v":"2013"},{"n":"2012","v":"2012"},{"n":"2011","v":"2011"}
      ]},
      {"key":"by","name":"排序","value":[{"n":"全部","v":""},{"n":"时间","v":"time"},{"n":"人气","v":"hits"},{"n":"评分","v":"score"}]}
      ],
    "4": [
      {"key":"area","name":"地区","value":[{"n":"全部","v":""},
        {"n":"大陆","v":"国产"},
        {"n":"日本","v":"日本"},
        {"n":"欧美","v":"欧美"},
        {"n":"其他","v":"其他"}
      ]},
      {"key":"year","name":"年份","value": [{"n":"全部","v":""},
        {"n":"2022","v":"2022"},{"n":"2021","v":"2021"},{"n":"2020","v":"2020"},{"n":"2019","v":"2019"},
        {"n":"2018","v":"2018"},{"n":"2017","v":"2017"},{"n":"2016","v":"2016"},{"n":"2015","v":"2015"},
        {"n":"2014","v":"2014"},{"n":"2013","v":"2013"},{"n":"2012","v":"2012"},{"n":"2011","v":"2011"}
      ]},
      {"key":"by","name":"排序","value":[{"n":"全部","v":""},{"n":"时间","v":"time"},{"n":"人气","v":"hits"},{"n":"评分","v":"score"}]}
    ],
    "6": [
      {"key":"area","name":"地区","value":[{"n":"全部","v":""},
        {"n":"大陆","v":"大陆"},
        {"n":"美国","v":"美国"},
        {"n":"法国","v":"法国"},
        {"n":"英国","v":"英国"},
        {"n":"德国","v":"德国"},
        {"n":"日本","v":"日本"},
        {"n":"韩国","v":"韩国"},
        {"n":"香港","v":"香港"},
        {"n":"台湾","v":"台湾"},
        {"n":"泰国","v":"泰国"},
        {"n":"印度","v":"印度"},
        {"n":"意大利","v":"意大利"},
        {"n":"西班牙","v":"西班牙"},
        {"n":"加拿大","v":"加拿大"},
        {"n":"其他","v":"其他"}
      ]},
      {"key":"year","name":"年份","value": [{"n":"全部","v":""},
        {"n":"2022","v":"2022"},{"n":"2021","v":"2021"},{"n":"2020","v":"2020"},{"n":"2019","v":"2019"},
        {"n":"2018","v":"2018"},{"n":"2017","v":"2017"},{"n":"2016","v":"2016"},{"n":"2015","v":"2015"},
        {"n":"2014","v":"2014"},{"n":"2013","v":"2013"},{"n":"2012","v":"2012"},{"n":"2011","v":"2011"}
      ]},
      {"key":"by","name":"排序","value":[{"n":"全部","v":""},{"n":"时间","v":"time"},{"n":"人气","v":"hits"},{"n":"评分","v":"score"}]}
    ],
    "7": [
      {"key":"area","name":"地区","value":[{"n":"全部","v":""},
        {"n":"大陆","v":"大陆"},
        {"n":"美国","v":"美国"},
        {"n":"法国","v":"法国"},
        {"n":"英国","v":"英国"},
        {"n":"德国","v":"德国"},
        {"n":"日本","v":"日本"},
        {"n":"韩国","v":"韩国"},
        {"n":"香港","v":"香港"},
        {"n":"台湾","v":"台湾"},
        {"n":"泰国","v":"泰国"},
        {"n":"印度","v":"印度"},
        {"n":"意大利","v":"意大利"},
        {"n":"西班牙","v":"西班牙"},
        {"n":"加拿大","v":"加拿大"},
        {"n":"其他","v":"其他"}
      ]},
      {"key":"year","name":"年份","value": [{"n":"全部","v":""},
        {"n":"2022","v":"2022"},{"n":"2021","v":"2021"},{"n":"2020","v":"2020"},{"n":"2019","v":"2019"},
        {"n":"2018","v":"2018"},{"n":"2017","v":"2017"},{"n":"2016","v":"2016"},{"n":"2015","v":"2015"},
        {"n":"2014","v":"2014"},{"n":"2013","v":"2013"},{"n":"2012","v":"2012"},{"n":"2011","v":"2011"}
      ]},
      {"key":"by","name":"排序","value":[{"n":"全部","v":""},{"n":"时间","v":"time"},{"n":"人气","v":"hits"},{"n":"评分","v":"score"}]}
    ],
    "8": [
      {"key":"area","name":"地区","value":[{"n":"全部","v":""},
        {"n":"大陆","v":"大陆"},
        {"n":"美国","v":"美国"},
        {"n":"法国","v":"法国"},
        {"n":"英国","v":"英国"},
        {"n":"德国","v":"德国"},
        {"n":"日本","v":"日本"},
        {"n":"韩国","v":"韩国"},
        {"n":"香港","v":"香港"},
        {"n":"台湾","v":"台湾"},
        {"n":"泰国","v":"泰国"},
        {"n":"印度","v":"印度"},
        {"n":"意大利","v":"意大利"},
        {"n":"西班牙","v":"西班牙"},
        {"n":"加拿大","v":"加拿大"},
        {"n":"其他","v":"其他"}
      ]},
      {"key":"year","name":"年份","value": [{"n":"全部","v":""},
        {"n":"2022","v":"2022"},{"n":"2021","v":"2021"},{"n":"2020","v":"2020"},{"n":"2019","v":"2019"},
        {"n":"2018","v":"2018"},{"n":"2017","v":"2017"},{"n":"2016","v":"2016"},{"n":"2015","v":"2015"},
        {"n":"2014","v":"2014"},{"n":"2013","v":"2013"},{"n":"2012","v":"2012"},{"n":"2011","v":"2011"}
      ]},
      {"key":"by","name":"排序","value":[{"n":"全部","v":""},{"n":"时间","v":"time"},{"n":"人气","v":"hits"},{"n":"评分","v":"score"}]}
    ],
    "9": [
      {"key":"area","name":"地区","value":[{"n":"全部","v":""},
        {"n":"大陆","v":"大陆"},
        {"n":"美国","v":"美国"},
        {"n":"法国","v":"法国"},
        {"n":"英国","v":"英国"},
        {"n":"德国","v":"德国"},
        {"n":"日本","v":"日本"},
        {"n":"韩国","v":"韩国"},
        {"n":"香港","v":"香港"},
        {"n":"台湾","v":"台湾"},
        {"n":"泰国","v":"泰国"},
        {"n":"印度","v":"印度"},
        {"n":"意大利","v":"意大利"},
        {"n":"西班牙","v":"西班牙"},
        {"n":"加拿大","v":"加拿大"},
        {"n":"其他","v":"其他"}
      ]},
      {"key":"year","name":"年份","value": [{"n":"全部","v":""},
        {"n":"2022","v":"2022"},{"n":"2021","v":"2021"},{"n":"2020","v":"2020"},{"n":"2019","v":"2019"},
        {"n":"2018","v":"2018"},{"n":"2017","v":"2017"},{"n":"2016","v":"2016"},{"n":"2015","v":"2015"},
        {"n":"2014","v":"2014"},{"n":"2013","v":"2013"},{"n":"2012","v":"2012"},{"n":"2011","v":"2011"}
      ]},
      {"key":"by","name":"排序","value":[{"n":"全部","v":""},{"n":"时间","v":"time"},{"n":"人气","v":"hits"},{"n":"评分","v":"score"}]}
    ],
    "10": [
      {"key":"area","name":"地区","value":[{"n":"全部","v":""},
        {"n":"大陆","v":"大陆"},
        {"n":"美国","v":"美国"},
        {"n":"法国","v":"法国"},
        {"n":"英国","v":"英国"},
        {"n":"德国","v":"德国"},
        {"n":"日本","v":"日本"},
        {"n":"韩国","v":"韩国"},
        {"n":"香港","v":"香港"},
        {"n":"台湾","v":"台湾"},
        {"n":"泰国","v":"泰国"},
        {"n":"印度","v":"印度"},
        {"n":"意大利","v":"意大利"},
        {"n":"西班牙","v":"西班牙"},
        {"n":"加拿大","v":"加拿大"},
        {"n":"其他","v":"其他"}
      ]},
      {"key":"year","name":"年份","value": [{"n":"全部","v":""},
        {"n":"2022","v":"2022"},{"n":"2021","v":"2021"},{"n":"2020","v":"2020"},{"n":"2019","v":"2019"},
        {"n":"2018","v":"2018"},{"n":"2017","v":"2017"},{"n":"2016","v":"2016"},{"n":"2015","v":"2015"},
        {"n":"2014","v":"2014"},{"n":"2013","v":"2013"},{"n":"2012","v":"2012"},{"n":"2011","v":"2011"}
      ]},
      {"key":"by","name":"排序","value":[{"n":"全部","v":""},{"n":"时间","v":"time"},{"n":"人气","v":"hits"},{"n":"评分","v":"score"}]}
    ],
    "11": [
      {"key":"area","name":"地区","value":[{"n":"全部","v":""},
        {"n":"大陆","v":"大陆"},
        {"n":"美国","v":"美国"},
        {"n":"法国","v":"法国"},
        {"n":"英国","v":"英国"},
        {"n":"德国","v":"德国"},
        {"n":"日本","v":"日本"},
        {"n":"韩国","v":"韩国"},
        {"n":"香港","v":"香港"},
        {"n":"台湾","v":"台湾"},
        {"n":"泰国","v":"泰国"},
        {"n":"印度","v":"印度"},
        {"n":"意大利","v":"意大利"},
        {"n":"西班牙","v":"西班牙"},
        {"n":"加拿大","v":"加拿大"},
        {"n":"其他","v":"其他"}
      ]},
      {"key":"year","name":"年份","value": [{"n":"全部","v":""},
        {"n":"2022","v":"2022"},{"n":"2021","v":"2021"},{"n":"2020","v":"2020"},{"n":"2019","v":"2019"},
        {"n":"2018","v":"2018"},{"n":"2017","v":"2017"},{"n":"2016","v":"2016"},{"n":"2015","v":"2015"},
        {"n":"2014","v":"2014"},{"n":"2013","v":"2013"},{"n":"2012","v":"2012"},{"n":"2011","v":"2011"}
      ]},
      {"key":"by","name":"排序","value":[{"n":"全部","v":""},{"n":"时间","v":"time"},{"n":"人气","v":"hits"},{"n":"评分","v":"score"}]}
    ],
    "12": [
      {"key":"area","name":"地区","value":[{"n":"全部","v":""},
        {"n":"大陆","v":"大陆"},
        {"n":"美国","v":"美国"},
        {"n":"法国","v":"法国"},
        {"n":"英国","v":"英国"},
        {"n":"德国","v":"德国"},
        {"n":"日本","v":"日本"},
        {"n":"韩国","v":"韩国"},
        {"n":"香港","v":"香港"},
        {"n":"台湾","v":"台湾"},
        {"n":"泰国","v":"泰国"},
        {"n":"印度","v":"印度"},
        {"n":"意大利","v":"意大利"},
        {"n":"西班牙","v":"西班牙"},
        {"n":"加拿大","v":"加拿大"},
        {"n":"其他","v":"其他"}
      ]},
      {"key":"year","name":"年份","value": [{"n":"全部","v":""},
        {"n":"2022","v":"2022"},{"n":"2021","v":"2021"},{"n":"2020","v":"2020"},{"n":"2019","v":"2019"},
        {"n":"2018","v":"2018"},{"n":"2017","v":"2017"},{"n":"2016","v":"2016"},{"n":"2015","v":"2015"},
        {"n":"2014","v":"2014"},{"n":"2013","v":"2013"},{"n":"2012","v":"2012"},{"n":"2011","v":"2011"}
      ]},
      {"key":"by","name":"排序","value":[{"n":"全部","v":""},{"n":"时间","v":"time"},{"n":"人气","v":"hits"},{"n":"评分","v":"score"}]}
    ],
    "13": [
      {"key":"year","name":"年份","value": [{"n":"全部","v":""},
        {"n":"2022","v":"2022"},{"n":"2021","v":"2021"},{"n":"2020","v":"2020"},{"n":"2019","v":"2019"},
        {"n":"2018","v":"2018"},{"n":"2017","v":"2017"},{"n":"2016","v":"2016"},{"n":"2015","v":"2015"},
        {"n":"2014","v":"2014"},{"n":"2013","v":"2013"},{"n":"2012","v":"2012"},{"n":"2011","v":"2011"}
      ]},
      {"key":"by","name":"排序","value":[{"n":"全部","v":""},{"n":"时间","v":"time"},{"n":"人气","v":"hits"},{"n":"评分","v":"score"}]}
    ],
    "14": [
      {"key":"year","name":"年份","value": [{"n":"全部","v":""},
        {"n":"2022","v":"2022"},{"n":"2021","v":"2021"},{"n":"2020","v":"2020"},{"n":"2019","v":"2019"},
        {"n":"2018","v":"2018"},{"n":"2017","v":"2017"},{"n":"2016","v":"2016"},{"n":"2015","v":"2015"},
        {"n":"2014","v":"2014"},{"n":"2013","v":"2013"},{"n":"2012","v":"2012"},{"n":"2011","v":"2011"}
      ]},
      {"key":"by","name":"排序","value":[{"n":"全部","v":""},{"n":"时间","v":"time"},{"n":"人气","v":"hits"},{"n":"评分","v":"score"}]}
    ],
    "15": [
      {"key":"year","name":"年份","value": [{"n":"全部","v":""},
        {"n":"2022","v":"2022"},{"n":"2021","v":"2021"},{"n":"2020","v":"2020"},{"n":"2019","v":"2019"},
        {"n":"2018","v":"2018"},{"n":"2017","v":"2017"},{"n":"2016","v":"2016"},{"n":"2015","v":"2015"},
        {"n":"2014","v":"2014"},{"n":"2013","v":"2013"},{"n":"2012","v":"2012"},{"n":"2011","v":"2011"}
      ]},
      {"key":"by","name":"排序","value":[{"n":"全部","v":""},{"n":"时间","v":"time"},{"n":"人气","v":"hits"},{"n":"评分","v":"score"}]}
    ],
    "16": [
      {"key":"year","name":"年份","value": [{"n":"全部","v":""},
        {"n":"2022","v":"2022"},{"n":"2021","v":"2021"},{"n":"2020","v":"2020"},{"n":"2019","v":"2019"},
        {"n":"2018","v":"2018"},{"n":"2017","v":"2017"},{"n":"2016","v":"2016"},{"n":"2015","v":"2015"},
        {"n":"2014","v":"2014"},{"n":"2013","v":"2013"},{"n":"2012","v":"2012"},{"n":"2011","v":"2011"}
      ]},
      {"key":"by","name":"排序","value":[{"n":"全部","v":""},{"n":"时间","v":"time"},{"n":"人气","v":"hits"},{"n":"评分","v":"score"}]}
      ]
  }
}